{
  "id": "anemia-hemolitica",
  "fullContent": {
    "epidemiologia": {
      "fatoresRisco": [],
      "citations": []
    },
    "quadroClinico": {
      "sintomasPrincipais": [],
      "sinaisExameFisico": [],
      "citations": []
    },
    "diagnostico": {
      "criterios": [
        "Anemia",
        "Aumento de reticulócitos",
        "LDH elevado",
        "Bilirrubina indireta elevada",
        "Haptoglobina baixa"
      ],
      "diagnosticoDiferencial": [],
      "examesLaboratoriais": [],
      "examesImagem": [],
      "outrosExames": [],
      "citations": []
    },
    "tratamento": {
      "objetivos": [],
      "naoFarmacologico": {
        "medidas": [
          "Tratar causa de base",
          "Evitar desencadeantes"
        ],
        "citations": []
      },
      "farmacologico": {
        "primeiraLinha": [
          {
            "classe": "Primeira linha (resumo)",
            "medicamentos": [
              "Corticosteroides se autoimune",
              "Transfusão se sintomático"
            ]
          }
        ],
        "citations": []
      }
    },
    "acompanhamento": {
      "frequenciaConsultas": "",
      "metasTerapeuticas": [],
      "criteriosEncaminhamento": [],
      "citations": []
    }
  },
  "citations": [],
  "lastUpdate": "2026-02"
}
